dataconfigs/__init__.py
dataconfigs/utils.py
dataconfigs/cli/__init__.py
dataconfigs/configs/__init__.py
dataconfigs/configs/config.py
dataconfigs/configs/configurable.py
dataconfigs/configs/params.py
dataconfigs/configs/tools.py
dataconfigs/io/__init__.py
dataconfigs-0.1.0.dist-info/METADATA
dataconfigs-0.1.0.dist-info/WHEEL
dataconfigs-0.1.0.dist-info/top_level.txt
dataconfigs-0.1.0.dist-info/RECORD
