Metadata-Version: 2.1
Name: dataconfigs
Version: 0.1.0
Summary: Turn your dataclasses into configs seamlessly.
Home-page: https://github.com/mantasu/dataconfigs
Author: Mantas Birškus
Author-email: mantix7@gmail.com
License: Apache
Project-URL: Documentation, https://mantasu.github.io/dataconfigs
Project-URL: Bug Tracker, https://github.com/mantasu/dataconfigs/issues
Keywords: python,config,configuration,configurable
Classifier: Topic :: Software Development :: Libraries :: Python Modules
Classifier: Development Status :: 2 - Pre-Alpha
Classifier: Intended Audience :: Science/Research
Classifier: Intended Audience :: Developers
Classifier: Intended Audience :: Information Technology
Classifier: Programming Language :: Python
Classifier: Programming Language :: Python :: 3
Classifier: Programming Language :: Python :: 3.12
Classifier: Programming Language :: Python :: 3.13
Classifier: Natural Language :: English
Classifier: License :: OSI Approved :: Apache Software License
Classifier: Operating System :: OS Independent
Classifier: Environment :: Console
Classifier: Environment :: MacOS X
Classifier: Environment :: Win32 (MS Windows)
Classifier: Environment :: Other Environment
Requires-Python: >=3.12
Requires-Dist: docstring-parser
